ancypwn_backend_windows_remote/__init__.py
ancypwn_backend_windows_remote/backend.py
ancypwn_backend_wsl2/__init__.py
ancypwn_backend_wsl2/backend.py
ancypwn_backend_windows_remote-0.0.2.dist-info/METADATA
ancypwn_backend_windows_remote-0.0.2.dist-info/WHEEL
ancypwn_backend_windows_remote-0.0.2.dist-info/top_level.txt
ancypwn_backend_windows_remote-0.0.2.dist-info/RECORD
