Metadata-Version: 2.1
Name: ancypwn-backend-windows-remote
Version: 0.0.2
Summary: ancypwn windows remote backend
Home-page: https://github.com/Escapingbug/ancypwn-backend-windows_remote
Author: Anciety
Author-email: anciety@pku.edu.cn
License: UNKNOWN
Platform: UNKNOWN
Requires-Dist: docker
Requires-Dist: appdirs
